{
    "name": "Genius of Brilliant Stars",
    "rarity": 5,
    "effects": [
        {
            "useNum": 2,
            "desc": "Increases <span style=\"color:#7788ff;\">Quantum</span> DMG by <nobr>#1[i]%</nobr>.",
            "params": [
                0.1
            ]
        },
        {
            "useNum": 4,
            "desc": "When the wearer deals DMG to the target enemy, ignores <nobr>#1[i]%</nobr> DEF. If the target enemy has <span style=\"color:#7788ff;\">Quantum</span> Weakness, the wearer additionally ignores <nobr>#2[i]%</nobr> DEF.",
            "params": [
                0.1,
                0.1
            ]
        }
    ],
    "pieces": {
        "1": {
            "name": "Genius's Ultraremote Sensing Visor",
            "maxRarity": 5,
            "type": "Head"
        },
        "2": {
            "name": "Genius's Frequency Catcher",
            "maxRarity": 5,
            "type": "Hands"
        },
        "3": {
            "name": "Genius's Metafield Suit",
            "maxRarity": 5,
            "type": "Body"
        },
        "4": {
            "name": "Genius's Gravity Walker",
            "maxRarity": 5,
            "type": "Feet"
        }
    }
}